COPYING
COPYING.LESSER
MANIFEST.in
NEWS.rst
README.rst
setup.cfg
setup.py
pyjulius3/__init__.py
pyjulius3/core.py
pyjulius3/exceptions.py
pyjulius3/infos.py
pyjulius3/models.py
pyjulius3.egg-info/PKG-INFO
pyjulius3.egg-info/SOURCES.txt
pyjulius3.egg-info/dependency_links.txt
pyjulius3.egg-info/top_level.txt