Metadata-Version: 1.1
Name: pyjulius3
Version: 0.4
Summary: Simple interface to connect to a julius module server
Home-page: https://github.com/bachmmmar/pyjulius
Author: Martin Bachmann
Author-email: bachmmar@gmail.com
License: LGPLv3
Keywords: julius speech recognition
Platform: UNKNOWN
Classifier: Development Status :: 4 - Beta
Classifier: License :: OSI Approved :: GNU Library or Lesser General Public License (LGPL)
Classifier: Intended Audience :: Developers
Classifier: Operating System :: OS Independent
Classifier: Programming Language :: Python :: 3.5
Classifier: Topic :: Software Development :: Libraries :: Python Modules
